solflatliner/__init__.py
solflatliner/cmd.py
solflatliner/compilerx.py
solflatliner/main.py
solflatliner-1.0.118.dist-info/LICENSE
solflatliner-1.0.118.dist-info/METADATA
solflatliner-1.0.118.dist-info/WHEEL
solflatliner-1.0.118.dist-info/entry_points.txt
solflatliner-1.0.118.dist-info/top_level.txt
solflatliner-1.0.118.dist-info/RECORD
