Metadata-Version: 2.1
Name: solflatliner
Version: 1.0.118
Summary: A Python package to unfold soldity code with imports into a single file.
Home-page: https://github.com/tokenchain/solidity-flatliner
Author: Jun-You Liu & Heskemo
Author-email: junyouliu9@gmail.com
License: MIT
Keywords: soldity solidity-unfolder solidity-flatliner               smart-contracts ethereum
Platform: UNKNOWN
Classifier: Development Status :: 3 - Alpha
Classifier: Intended Audience :: Developers
Classifier: License :: OSI Approved :: MIT License
Classifier: Programming Language :: Python :: 3
Classifier: Programming Language :: Python :: 3.6
Classifier: Programming Language :: Python :: 3.7
Classifier: Programming Language :: Python :: 3.8
Classifier: Programming Language :: Python :: 3.9
Classifier: Topic :: Software Development :: Code Generators
Classifier: Topic :: Software Development :: Libraries :: Python Modules
Requires-Python: >=3.6,<4
